colorinput/__init__.py
colorinput/apps.py
colorinput/models.py
colorinput/tests.py
colorinput/forms/__init__.py
colorinput/forms/fields.py
colorinput/forms/widgets.py
colorinput/templates/colorinput/widgets/colorinput.html
django_colorinput-0.2.dist-info/LICENCE
django_colorinput-0.2.dist-info/METADATA
django_colorinput-0.2.dist-info/WHEEL
django_colorinput-0.2.dist-info/top_level.txt
django_colorinput-0.2.dist-info/RECORD
