Metadata-Version: 2.1
Name: django-colorinput
Version: 0.2
Summary: Color fields for Django models and forms using HTML5 native color type input elements
Home-page: https://github.com/der-gabe/django-colorinput
Author: Gabriel Niebler
Author-email: gabriel.niebler@gmail.com
License: UNKNOWN
Platform: UNKNOWN
Classifier: Framework :: Django
Classifier: License :: OSI Approved :: GNU General Public License v3 (GPLv3)
Classifier: Operating System :: OS Independent
Classifier: Programming Language :: Python :: 3
Requires-Python: >=3.6
